pynasapower/__init__.py
pynasapower/geometry.py
pynasapower/get_data.py
pynasapower-0.0.1a1.dist-info/LICENSE
pynasapower-0.0.1a1.dist-info/METADATA
pynasapower-0.0.1a1.dist-info/WHEEL
pynasapower-0.0.1a1.dist-info/top_level.txt
pynasapower-0.0.1a1.dist-info/RECORD
